computer_use/__init__.py
computer_use/loop.py
computer_use/prompt.py
computer_use/server.py
computer_use/tools/__init__.py
computer_use/tools/base.py
computer_use/tools/bash.py
computer_use/tools/collection.py
computer_use/tools/computer.py
computer_use/tools/edit.py
computer_use/tools/run.py
computer_agent-0.1.1.dist-info/LICENSE
computer_agent-0.1.1.dist-info/METADATA
computer_agent-0.1.1.dist-info/WHEEL
computer_agent-0.1.1.dist-info/top_level.txt
computer_agent-0.1.1.dist-info/RECORD
