Metadata-Version: 2.2
Name: computer-agent
Version: 0.1.1
Summary: Giving Agents Computers
Author: b
Author-email: bb@fea.st
License: MIT
Classifier: Programming Language :: Python :: 3
Classifier: Operating System :: OS Independent
Requires-Python: >=3.8
License-File: LICENSE
Requires-Dist: anthropic>=0.19.0
Requires-Dist: jsonschema==4.22.0
Requires-Dist: fastapi>=0.115.0
Requires-Dist: uvicorn>=0.15.0
Requires-Dist: sse-starlette>=1.0.0
Dynamic: author
Dynamic: author-email
Dynamic: classifier
Dynamic: description
Dynamic: description-content-type
Dynamic: license
Dynamic: requires-dist
Dynamic: requires-python
Dynamic: summary
